Maintera/__init__.py
Maintera/activation_functions.py
Maintera/nn_model.py
Maintera-1.0.dist-info/METADATA
Maintera-1.0.dist-info/WHEEL
Maintera-1.0.dist-info/top_level.txt
Maintera-1.0.dist-info/RECORD
