Metadata-Version: 2.1
Name: Maintera
Version: 1.0
Requires-Dist: numpy
